LICENSE.txt
README.md
setup.cfg
setup.py
bin/neoden_kicad
neoden_kicad/__init__.py
neoden_kicad/converter.py
neoden_kicad.egg-info/PKG-INFO
neoden_kicad.egg-info/SOURCES.txt
neoden_kicad.egg-info/dependency_links.txt
neoden_kicad.egg-info/top_level.txt