Metadata-Version: 2.1
Name: neoden-kicad
Version: 1.0.0a2
Summary: Converter for Neoden Pick and Place machine
Home-page: http://github.com/elec-otago/neoden-yy1-kicad
Author: Tim Molteno, Phill Brown
Author-email: tim@elec.ac.nz
License: GPLv3
Classifier: Development Status :: 4 - Beta
Classifier: Topic :: Scientific/Engineering
Classifier: License :: OSI Approved :: GNU General Public License v3 (GPLv3)
Classifier: Programming Language :: Python :: 3
Classifier: Intended Audience :: End Users/Desktop
License-File: LICENSE.txt
